opsys_electrical_cabinet/__init__.py
opsys_electrical_cabinet/electrical_cabinet.py
opsys_electrical_cabinet-0.0.3.dist-info/LICENSE
opsys_electrical_cabinet-0.0.3.dist-info/METADATA
opsys_electrical_cabinet-0.0.3.dist-info/WHEEL
opsys_electrical_cabinet-0.0.3.dist-info/top_level.txt
opsys_electrical_cabinet-0.0.3.dist-info/RECORD
